example_pkg/__init__.py
example_pkg/hi_example.py
example_pkg_dankersw-0.0.4.dist-info/LICENSE
example_pkg_dankersw-0.0.4.dist-info/METADATA
example_pkg_dankersw-0.0.4.dist-info/WHEEL
example_pkg_dankersw-0.0.4.dist-info/top_level.txt
example_pkg_dankersw-0.0.4.dist-info/RECORD
